nonebot_plugin_lazytea/__init__.py
nonebot_plugin_lazytea/bridge.py
nonebot_plugin_lazytea/sdk.py
nonebot_plugin_lazytea/ipc/__init__.py
nonebot_plugin_lazytea/ipc/envhandler.py
nonebot_plugin_lazytea/ipc/func_call.py
nonebot_plugin_lazytea/ipc/models.py
nonebot_plugin_lazytea/ipc/server.py
nonebot_plugin_lazytea/ui/main_window.py
nonebot_plugin_lazytea/ui/protocol.py
nonebot_plugin_lazytea/ui/sdk.py
nonebot_plugin_lazytea/ui/pages/__init__.py
nonebot_plugin_lazytea/ui/pages/base_page.py
nonebot_plugin_lazytea/ui/pages/bot_info_page.py
nonebot_plugin_lazytea/ui/pages/message_page.py
nonebot_plugin_lazytea/ui/pages/overview_page.py
nonebot_plugin_lazytea/ui/pages/plugin_page.py
nonebot_plugin_lazytea/ui/pages/Bubble/MessageBubble.py
nonebot_plugin_lazytea/ui/pages/background/plugin_recorder.py
nonebot_plugin_lazytea/ui/pages/background/quit.py
nonebot_plugin_lazytea/ui/pages/background/start.py
nonebot_plugin_lazytea/ui/pages/utils/client.py
nonebot_plugin_lazytea/ui/pages/utils/env.py
nonebot_plugin_lazytea/ui/pages/utils/plugin_html.py
nonebot_plugin_lazytea/ui/pages/utils/tealog.py
nonebot_plugin_lazytea/ui/pages/utils/token.py
nonebot_plugin_lazytea/ui/pages/utils/version_check.py
nonebot_plugin_lazytea/ui/pages/utils/BotTools/__init__.py
nonebot_plugin_lazytea/ui/pages/utils/BotTools/color.py
nonebot_plugin_lazytea/ui/pages/utils/BotTools/counter.py
nonebot_plugin_lazytea/ui/pages/utils/BotTools/timer.py
nonebot_plugin_lazytea/ui/pages/utils/Qcomponents/light_http.py
nonebot_plugin_lazytea/ui/pages/utils/Qcomponents/networkmanager.py
nonebot_plugin_lazytea/ui/pages/utils/Qcomponents/nonwheel.py
nonebot_plugin_lazytea/ui/pages/utils/Qcomponents/MessageBox/__init__.py
nonebot_plugin_lazytea/ui/pages/utils/Qcomponents/MessageBox/message_box.py
nonebot_plugin_lazytea/ui/pages/utils/Qcomponents/MessageBox/model.py
nonebot_plugin_lazytea/ui/pages/utils/client_login/config_manager.py
nonebot_plugin_lazytea/ui/pages/utils/client_login/login_ui.py
nonebot_plugin_lazytea-0.1.2.dist-info/METADATA
nonebot_plugin_lazytea-0.1.2.dist-info/WHEEL
nonebot_plugin_lazytea-0.1.2.dist-info/top_level.txt
nonebot_plugin_lazytea-0.1.2.dist-info/RECORD
