Metadata-Version: 2.4
Name: nonebot_plugin_lazytea
Version: 0.1.2
Summary: 适用于nonebot2的GUI
Requires-Python: >=3.10
Requires-Dist: beautifulsoup4>=4.13.3
Requires-Dist: markdown2>=2.5.3
Requires-Dist: nonebot2>=2.4.2
Requires-Dist: pyside6>=6.9.1
Requires-Dist: aiofiles>=24.1.0
Requires-Dist: websockets>=15.0.1
Requires-Dist: pydantic>=2.0.0
Requires-Dist: apsw>=3.50.1.0
Requires-Dist: nonebot-plugin-localstore>=0.7.4
Requires-Dist: xxhash>=3.5.0
Requires-Dist: nonebot-plugin-uninfo>=0.8.2
Requires-Dist: nonebot-plugin-alconna>=0.59.0
Requires-Dist: jinja2>=3.1.6
Requires-Dist: portpicker>=1.6.0
Requires-Dist: orjson>=3.11.2
